db_schema_mcp/__init__.py
db_schema_mcp/cli.py
db_schema_mcp/config.py
db_schema_mcp/mcp_server.py
db_schema_mcp/connections/__init__.py
db_schema_mcp/connections/base.py
db_schema_mcp/connections/factory.py
db_schema_mcp/connections/mysql.py
db_schema_mcp/connections/oracle.py
db_schema_mcp/connections/postgres.py
db_schema_mcp/connections/sqlite.py
db_schema_mcp/tools/__init__.py
db_schema_mcp/tools/describe_table.py
db_schema_mcp/tools/list_connections.py
db_schema_mcp/tools/list_tables.py
db_schema_mcp-1.0.0.dist-info/METADATA
db_schema_mcp-1.0.0.dist-info/WHEEL
db_schema_mcp-1.0.0.dist-info/entry_points.txt
db_schema_mcp-1.0.0.dist-info/licenses/LICENSE
db_schema_mcp-1.0.0.dist-info/RECORD
