Metadata-Version: 2.4
Name: db-schema-mcp
Version: 1.0.0
Summary: 用于查询数据库表结构的 Model Context Protocol 服务器
Project-URL: Homepage, https://github.com/soberw/db-schema-mcp
Project-URL: Documentation, https://github.com/soberw/db-schema-mcp#readme
Project-URL: Repository, https://github.com/soberw/db-schema-mcp
Project-URL: Issues, https://github.com/soberw/db-schema-mcp/issues
Author: soberw
License: MIT
License-File: LICENSE
Keywords: database,mcp,mysql,oracle,postgresql,schema,sqlite
Classifier: Development Status :: 3 - Alpha
Classifier: Intended Audience :: Developers
Classifier: License :: OSI Approved :: MIT License
Classifier: Programming Language :: Python :: 3
Classifier: Programming Language :: Python :: 3.12
Classifier: Programming Language :: Python :: 3.13
Classifier: Topic :: Database
Classifier: Topic :: Software Development :: Libraries :: Python Modules
Requires-Python: >=3.12
Requires-Dist: aiomysql>=0.2.0
Requires-Dist: mcp>=0.9.0
Requires-Dist: oracledb>=2.0.0
Requires-Dist: psycopg[binary]>=3.2.0
Requires-Dist: pyyaml>=6.0.0
Provides-Extra: dev
Requires-Dist: mypy>=1.10.0; extra == 'dev'
Requires-Dist: pytest-asyncio>=0.23.0; extra == 'dev'
Requires-Dist: pytest-cov>=5.0.0; extra == 'dev'
Requires-Dist: pytest>=8.0.0; extra == 'dev'
Requires-Dist: ruff>=0.6.0; extra == 'dev'
Requires-Dist: testcontainers>=4.0.0; extra == 'dev'
